graffiti_lookup/__init__.py
graffiti_lookup/__main__.py
graffiti_lookup/client.py
graffiti_lookup/models.py
graffiti_lookup_nyc-1.0.3.dist-info/licenses/LICENSE
tests/__init__.py
tests/test_client.py
tests/test_main_cli.py
tests/test_models.py
graffiti_lookup_nyc-1.0.3.dist-info/METADATA
graffiti_lookup_nyc-1.0.3.dist-info/WHEEL
graffiti_lookup_nyc-1.0.3.dist-info/entry_points.txt
graffiti_lookup_nyc-1.0.3.dist-info/top_level.txt
graffiti_lookup_nyc-1.0.3.dist-info/RECORD
