Metadata-Version: 2.4
Name: graffiti-lookup-nyc
Version: 1.0.3
Summary: Query NYC 311 Graffiti Cleanup Requests via CLI and Python API.
Home-page: https://github.com/njamaleddine/graffiti-lookup-nyc
Author: Nabil Jamaleddine
Author-email: me@nabiljamaleddine.com
Classifier: Programming Language :: Python :: 3
Classifier: License :: OSI Approved :: MIT License
Classifier: Operating System :: OS Independent
Requires-Python: >=3.8
License-File: LICENSE
Requires-Dist: httpx<0.27,>=0.23
Requires-Dist: beautifulsoup4<5.0,>=4.9
Dynamic: author
Dynamic: author-email
Dynamic: classifier
Dynamic: description
Dynamic: description-content-type
Dynamic: home-page
Dynamic: license-file
Dynamic: requires-dist
Dynamic: requires-python
Dynamic: summary
